pmpred/__init__.py
pmpred/main.py
pmpred/model/__init__.py
pmpred/model/ldpred.py
pmpred/model/pmldpred.py
pmpred/model/pmprscs.py
pmpred/model/predict.py
pmpred/model/prscs.py
pmpred/simulation/__init__.py
pmpred/simulation/generate.py
pmpred/snp_read/__init__.py
pmpred/snp_read/check.py
pmpred/snp_read/filter.py
pmpred/snp_read/read.py
pmpred/snp_read/write.py
PMpred-1.0.4.dist-info/LICENSE.txt
PMpred-1.0.4.dist-info/METADATA
PMpred-1.0.4.dist-info/WHEEL
PMpred-1.0.4.dist-info/entry_points.txt
PMpred-1.0.4.dist-info/top_level.txt
PMpred-1.0.4.dist-info/RECORD
