Metadata-Version: 2.1
Name: PMpred
Version: 1.0.4
Summary: A Python package that adjusts GWAS summary statistics for the effects of Sparse Precision Matrix (PM)
Home-page: https://github.com/WiuYuan/pmpred
Author: Wen Yuan
Author-email: wiuwenyuan@gmail.com
Keywords: Polygenic Risk Scores,GWAS,Linkage Disequilibrium,Risk Prediction,Precision Matrix
Requires-Python: >=3.6
License-File: LICENSE.txt
Requires-Dist: numpy
Requires-Dist: scipy
Requires-Dist: joblib
